{
  "users": [
    { "username": "user1", "password": "iX4TVju1zsaqmi6" },
    { "username": "user2", "password": "6ZJdi9CGvXerdfL" },
    { "username": "user3", "password": "ghmnFzOwk6hn9CD" },
    { "username": "user4", "password": "QydHTCPIOQkAfyz" },
    { "username": "user5", "password": "TaBJkMbce9MrT6K" },
    { "username": "user6", "password": "eIY9Ix0GTwKTqU7" },
    { "username": "user7", "password": "S6GwW6HvIW1X6GR" },
    { "username": "user8", "password": "MuapkYXkujVj3xL" },
    { "username": "user9", "password": "Vr42NKmX3lWE6le" },
    { "username": "user10", "password": "SljQH9lqQ7TA8fb" }
  ]
}
